empirica_mcp/epistemic_middleware.py
empirica_mcp/server.py
empirica_mcp/epistemic/__init__.py
empirica_mcp/epistemic/cli_prompt_templates.py
empirica_mcp/epistemic/mcp_response_templates.py
empirica_mcp/epistemic/modes.py
empirica_mcp/epistemic/personality.py
empirica_mcp/epistemic/router.py
empirica_mcp/epistemic/shared_vector_semantics.py
empirica_mcp/epistemic/state_machine.py
empirica_mcp-1.4.2.dist-info/METADATA
empirica_mcp-1.4.2.dist-info/WHEEL
empirica_mcp-1.4.2.dist-info/entry_points.txt
empirica_mcp-1.4.2.dist-info/top_level.txt
empirica_mcp-1.4.2.dist-info/RECORD
