Metadata-Version: 2.4
Name: empirica-mcp
Version: 1.4.2
Summary: MCP server for Empirica epistemic framework
Author: David S. L. Van Assche
License-Expression: MIT
Project-URL: Homepage, https://github.com/Nubaeon/empirica
Project-URL: Documentation, https://github.com/Nubaeon/empirica/tree/main/docs
Project-URL: Repository, https://github.com/Nubaeon/empirica
Project-URL: Issues, https://github.com/Nubaeon/empirica/issues
Keywords: mcp,empirica,epistemic,ai,metacognition
Classifier: Development Status :: 5 - Production/Stable
Classifier: Intended Audience :: Developers
Classifier: Programming Language :: Python :: 3
Classifier: Programming Language :: Python :: 3.11
Classifier: Programming Language :: Python :: 3.12
Classifier: Topic :: Software Development :: Libraries :: Python Modules
Requires-Python: >=3.11
Requires-Dist: empirica>=1.4.2
Requires-Dist: mcp>=1.0.0
